discoPy/__init__.py
discoPy/__version__.py
discoPy/client.py
discoPy/ws_client.py
discoPy/application/__init__.py
discoPy/application/application.py
discoPy/base_request/__init__.py
discoPy/base_request/base_request.py
discoPy/channel/__init__.py
discoPy/channel/channel.py
discoPy/core/WSClient.py
discoPy/core/__init__.py
discoPy/core/base_client.py
discoPy/core/application/__init__.py
discoPy/core/application/application.py
discoPy/core/channel/__init__.py
discoPy/core/channel/channel.py
discoPy/core/guild/__init__.py
discoPy/core/guild/guild.py
discoPy/core/stage/__init__.py
discoPy/core/stage/stage.py
discoPy/core/user/__init__.py
discoPy/core/user/user.py
discoPy/core/webhook/__init__.py
discoPy/core/webhook/webhook.py
discoPy/guild/__init__.py
discoPy/guild/guild.py
discoPy/rest/__init__.py
discoPy/rest/client.py
discoPy/rest/ws_client.py
discoPy/rest/application/__init__.py
discoPy/rest/application/application.py
discoPy/rest/base_request/__init__.py
discoPy/rest/base_request/base_request.py
discoPy/rest/channel/__init__.py
discoPy/rest/channel/channel.py
discoPy/rest/guild/__init__.py
discoPy/rest/guild/guild.py
discoPy/rest/stage/__init__.py
discoPy/rest/stage/stage.py
discoPy/rest/user/__init__.py
discoPy/rest/user/user.py
discoPy/rest/webhook/__init__.py
discoPy/rest/webhook/webhook.py
discoPy/stage/__init__.py
discoPy/stage/stage.py
discoPy/user/__init__.py
discoPy/user/user.py
discoPy/utils/__init__.py
discoPy/utils/attachment.py
discoPy/utils/embend.py
discoPy/utils/intents.py
discoPy/utils/permissions.py
discoPy/webhook/__init__.py
discoPy/webhook/webhook.py
python_discord_client-0.7.3.8.dist-info/LICENSE
python_discord_client-0.7.3.8.dist-info/METADATA
python_discord_client-0.7.3.8.dist-info/WHEEL
python_discord_client-0.7.3.8.dist-info/top_level.txt
python_discord_client-0.7.3.8.dist-info/RECORD
