Metadata-Version: 2.1
Name: python-discord-client
Version: 0.7.3.8
Summary: Collection of Discord related clients and methods.
Home-page: https://github.com/btschwertfeger/python-discord-client
Author: Benjamin Thomas Schwertfeger
Author-email: development@b-schwertfeger.de
License: MIT
Platform: UNKNOWN
Classifier: License :: OSI Approved :: MIT License
Classifier: Programming Language :: Python
Classifier: Programming Language :: Python :: 3.7
Requires-Python: >=3.7.0
License-File: LICENSE
Requires-Dist: requests
Requires-Dist: websockets
Requires-Dist: asyncio (>=3.4)
Requires-Dist: aiohttp
